dharitri_sdk_cli/__init__.py
dharitri_sdk_cli/args_converter.py
dharitri_sdk_cli/args_validation.py
dharitri_sdk_cli/cli.py
dharitri_sdk_cli/cli_config.py
dharitri_sdk_cli/cli_config_env.py
dharitri_sdk_cli/cli_config_wallet.py
dharitri_sdk_cli/cli_contracts.py
dharitri_sdk_cli/cli_data.py
dharitri_sdk_cli/cli_delegation.py
dharitri_sdk_cli/cli_deps.py
dharitri_sdk_cli/cli_dns.py
dharitri_sdk_cli/cli_faucet.py
dharitri_sdk_cli/cli_get.py
dharitri_sdk_cli/cli_governance.py
dharitri_sdk_cli/cli_ledger.py
dharitri_sdk_cli/cli_localnet.py
dharitri_sdk_cli/cli_multisig.py
dharitri_sdk_cli/cli_output.py
dharitri_sdk_cli/cli_password.py
dharitri_sdk_cli/cli_shared.py
dharitri_sdk_cli/cli_tokens.py
dharitri_sdk_cli/cli_transactions.py
dharitri_sdk_cli/cli_validator_wallet.py
dharitri_sdk_cli/cli_validators.py
dharitri_sdk_cli/cli_wallet.py
dharitri_sdk_cli/config.py
dharitri_sdk_cli/config_env.py
dharitri_sdk_cli/config_wallet.py
dharitri_sdk_cli/constants.py
dharitri_sdk_cli/contract_verification.py
dharitri_sdk_cli/cosign_transaction.py
dharitri_sdk_cli/dns.py
dharitri_sdk_cli/docker.py
dharitri_sdk_cli/downloader.py
dharitri_sdk_cli/errors.py
dharitri_sdk_cli/guardian_relayer_data.py
dharitri_sdk_cli/guards.py
dharitri_sdk_cli/interfaces.py
dharitri_sdk_cli/myprocess.py
dharitri_sdk_cli/sign_verify.py
dharitri_sdk_cli/signing_wrapper.py
dharitri_sdk_cli/simulation.py
dharitri_sdk_cli/transactions.py
dharitri_sdk_cli/utils.py
dharitri_sdk_cli/ux.py
dharitri_sdk_cli/version.py
dharitri_sdk_cli/workstation.py
dharitri_sdk_cli/dependencies/__init__.py
dharitri_sdk_cli/dependencies/install.py
dharitri_sdk_cli/dependencies/modules.py
dharitri_sdk_cli/dependencies/resolution.py
dharitri_sdk_cli/localnet/__init__.py
dharitri_sdk_cli/localnet/config_default.py
dharitri_sdk_cli/localnet/config_general.py
dharitri_sdk_cli/localnet/config_networking.py
dharitri_sdk_cli/localnet/config_part.py
dharitri_sdk_cli/localnet/config_root.py
dharitri_sdk_cli/localnet/config_sharding.py
dharitri_sdk_cli-0.0.4.dist-info/METADATA
dharitri_sdk_cli-0.0.4.dist-info/WHEEL
dharitri_sdk_cli-0.0.4.dist-info/entry_points.txt
dharitri_sdk_cli-0.0.4.dist-info/licenses/LICENSE
dharitri_sdk_cli-0.0.4.dist-info/RECORD
