Metadata-Version: 2.4
Name: dharitri-sdk-cli
Version: 0.0.4
Summary: DharitrI Smart Contracts Tools
Project-URL: Homepage, https://github.com/TerraDharitri/drt-py-sdk-cli
Author: DharitrI
License-Expression: MIT
License-File: LICENSE
Classifier: Intended Audience :: Developers
Classifier: License :: OSI Approved :: MIT License
Classifier: Operating System :: OS Independent
Classifier: Programming Language :: Python :: 3
Requires-Python: >=3.10
Requires-Dist: argcomplete==3.2.2
Requires-Dist: dharitri-py-sdk[ledger]==0.0.6
Requires-Dist: ledgercomm[hid]
Requires-Dist: requests<3.0.0,>=2.32.0
Requires-Dist: rich==13.3.4
Requires-Dist: toml>=0.10.2
